{
  "main": {
    "id": "985f5302963a78d0",
    "type": "split",
    "children": [
      {
        "id": "5174a030aa33df34",
        "type": "tabs",
        "children": [
          {
            "id": "14598c9159e2bc62",
            "type": "leaf",
            "state": {
              "type": "markdown",
              "state": {
                "file": "Drone Simulation Setup.md",
                "mode": "source",
                "source": false
              }
            }
          }
        ]
      }
    ],
    "direction": "vertical"
  },
  "left": {
    "id": "9228f1911c0d7dae",
    "type": "split",
    "children": [
      {
        "id": "8dd49b4ca873e669",
        "type": "tabs",
        "children": [
          {
            "id": "ada787889b1ff342",
            "type": "leaf",
            "state": {
              "type": "file-explorer",
              "state": {
                "sortOrder": "alphabetical"
              }
            }
          },
          {
            "id": "7cf029c9be0aeed7",
            "type": "leaf",
            "state": {
              "type": "search",
              "state": {
                "query": "",
                "matchingCase": false,
                "explainSearch": false,
                "collapseAll": false,
                "extraContext": false,
                "sortOrder": "alphabetical"
              }
            }
          },
          {
            "id": "ed6894c9d623b521",
            "type": "leaf",
            "state": {
              "type": "bookmarks",
              "state": {}
            }
          }
        ]
      }
    ],
    "direction": "horizontal",
    "width": 300
  },
  "right": {
    "id": "999d369b191743eb",
    "type": "split",
    "children": [
      {
        "id": "d7805a490943d43d",
        "type": "tabs",
        "children": [
          {
            "id": "73abe956165a8253",
            "type": "leaf",
            "state": {
              "type": "backlink",
              "state": {
                "file": "Drone Simulation Setup.md",
                "collapseAll": false,
                "extraContext": false,
                "sortOrder": "alphabetical",
                "showSearch": false,
                "searchQuery": "",
                "backlinkCollapsed": false,
                "unlinkedCollapsed": true
              }
            }
          },
          {
            "id": "607f54c561663b2f",
            "type": "leaf",
            "state": {
              "type": "outgoing-link",
              "state": {
                "file": "Drone Simulation Setup.md",
                "linksCollapsed": false,
                "unlinkedCollapsed": true
              }
            }
          },
          {
            "id": "408c9ec765c5f03e",
            "type": "leaf",
            "state": {
              "type": "tag",
              "state": {
                "sortOrder": "frequency",
                "useHierarchy": true
              }
            }
          },
          {
            "id": "d8ab7e1d76b8051f",
            "type": "leaf",
            "state": {
              "type": "outline",
              "state": {
                "file": "Drone Simulation Setup.md"
              }
            }
          }
        ]
      }
    ],
    "direction": "horizontal",
    "width": 300,
    "collapsed": true
  },
  "left-ribbon": {
    "hiddenItems": {
      "switcher:Open quick switcher": false,
      "graph:Open graph view": false,
      "canvas:Create new canvas": false,
      "daily-notes:Open today's daily note": false,
      "templates:Insert template": false,
      "command-palette:Open command palette": false
    }
  },
  "active": "14598c9159e2bc62",
  "lastOpenFiles": [
    "Nico Other ToDo Stuff.md",
    "Other ROS2 Stuff.md",
    "Drone Simulation Setup.md"
  ]
}